odoo/addons/stock_production_lot_quantity_tree/README.rst
odoo/addons/stock_production_lot_quantity_tree/__init__.py
odoo/addons/stock_production_lot_quantity_tree/__manifest__.py
odoo/addons/stock_production_lot_quantity_tree/i18n/stock_production_lot_quantity_tree.pot
odoo/addons/stock_production_lot_quantity_tree/readme/CONTRIBUTORS.rst
odoo/addons/stock_production_lot_quantity_tree/readme/DESCRIPTION.rst
odoo/addons/stock_production_lot_quantity_tree/static/description/icon.png
odoo/addons/stock_production_lot_quantity_tree/static/description/index.html
odoo/addons/stock_production_lot_quantity_tree/views/stock_production_lot.xml
odoo13_addon_stock_production_lot_quantity_tree-13.0.1.0.1.dev3.dist-info/METADATA
odoo13_addon_stock_production_lot_quantity_tree-13.0.1.0.1.dev3.dist-info/WHEEL
odoo13_addon_stock_production_lot_quantity_tree-13.0.1.0.1.dev3.dist-info/top_level.txt
odoo13_addon_stock_production_lot_quantity_tree-13.0.1.0.1.dev3.dist-info/RECORD
